pyradiosky/__init__.py
pyradiosky/cli.py
pyradiosky/skymodel.py
pyradiosky/spherical_coords_transforms.py
pyradiosky/utils.py
pyradiosky/data/__init__.py
pyradiosky/data/extended_source_test.sav
pyradiosky/data/fhd_catalog.sav
pyradiosky/data/fhd_catalog_bad.sav
pyradiosky/data/fhd_catalog_no_extend.sav
pyradiosky/data/fhd_catalog_with_beam_values.sav
pyradiosky/data/fhd_source_array.sav
pyradiosky/data/gleam_50srcs.vot
pyradiosky/data/gsm_galactic.skyh5
pyradiosky/data/gsm_icrs.skyh5
pyradiosky/data/healpix_disk.skyh5
pyradiosky/data/mock_hera_text_2458098.27471.txt
pyradiosky/data/old_skyh5_point_sources.skyh5
pyradiosky/data/pointsource_catalog.txt
pyradiosky/data/simple_test.vot
pyradiosky/data/single_source_old.vot
pyradiosky-1.1.0.dist-info/licenses/LICENSE
pyradiosky-1.1.0.dist-info/METADATA
pyradiosky-1.1.0.dist-info/WHEEL
pyradiosky-1.1.0.dist-info/entry_points.txt
pyradiosky-1.1.0.dist-info/top_level.txt
pyradiosky-1.1.0.dist-info/RECORD
