Metadata-Version: 2.4
Name: pyradiosky
Version: 1.1.0
Summary: Python objects and interfaces for representing diffuse, extended and compact astrophysical radio sources
Author-email: Bryna Hazelton <brynah@phys.washington.edu>, Matthew Kolopanis <mjkolopa@asu.edu>, Jonathan Pober <jonathan_pober@brown.edu>, Adam Lanman <alanman@mit.edu>
Maintainer-email: Bryna Hazelton <brynah@phys.washington.edu>, Matthew Kolopanis <mjkolopa@asu.edu>
Project-URL: Repository, https://github.com/RadioAstronomySoftwareGroup/pyradiosky
Project-URL: Documentation, https://pyradiosky.readthedocs.io/
Keywords: radio astronomy
Classifier: License :: OSI Approved :: BSD License
Classifier: Development Status :: 5 - Production/Stable
Classifier: Intended Audience :: Science/Research
Classifier: License :: OSI Approved :: BSD License
Classifier: Programming Language :: Python :: 3.11
Classifier: Programming Language :: Python :: 3.12
Classifier: Programming Language :: Python :: 3.13
Classifier: Topic :: Scientific/Engineering :: Astronomy
Requires-Python: >=3.11
License-File: LICENSE
Requires-Dist: astropy>=6.0
Requires-Dist: h5py>=3.7
Requires-Dist: numpy>=1.23
Requires-Dist: pyuvdata>=3.1.0
Requires-Dist: scipy>=1.9
Requires-Dist: setuptools>=64
Requires-Dist: setuptools_scm>=8.1
Provides-Extra: healpix
Requires-Dist: astropy-healpix>=1.0.2; extra == "healpix"
Provides-Extra: astroquery
Requires-Dist: astroquery>=0.4.4; extra == "astroquery"
Provides-Extra: lunarsky
Requires-Dist: lunarsky>=0.2.5; extra == "lunarsky"
Provides-Extra: all
Requires-Dist: pyradiosky[astroquery,healpix,lunarsky]; extra == "all"
Provides-Extra: test
Requires-Dist: coverage; extra == "test"
Requires-Dist: pre-commit; extra == "test"
Requires-Dist: pytest; extra == "test"
Requires-Dist: pytest-cov; extra == "test"
Provides-Extra: doc
Requires-Dist: matplotlib; extra == "doc"
Requires-Dist: pypandoc; extra == "doc"
Requires-Dist: sphinx; extra == "doc"
Provides-Extra: dev
Requires-Dist: pyradiosky[all,doc,test]; extra == "dev"
Dynamic: license-file
